mlx/__init__.py
mlx/api/__init__.py
mlx/api/launcher.py
mlx/api/profile.py
mlx/api/workspace.py
mlx/cli.py
mlx/config.py
mlx/misc/__init__.py
mlx/misc/_types.py
mlx/misc/util.py
mlx/models/__init__.py
mlx/models/base.py
mlx/models/credentials.py
mlx/models/profile.py
mlx/session.py
multilogin-2.0.0.dist-info/LICENSE
multilogin-2.0.0.dist-info/METADATA
multilogin-2.0.0.dist-info/WHEEL
multilogin-2.0.0.dist-info/entry_points.txt
multilogin-2.0.0.dist-info/RECORD
