Metadata-Version: 2.1
Name: multilogin
Version: 2.0.0
Summary: 
Author: teocns
Author-email: teocns@gmail.com
Requires-Python: >=3.11,<3.12
Classifier: Programming Language :: Python :: 3
Classifier: Programming Language :: Python :: 3.11
Requires-Dist: pydantic
Requires-Dist: pydantic-settings (>=2.3.4,<3.0.0)
Requires-Dist: requests
Requires-Dist: urllib3 (>=2.2.2,<3.0.0)
